lib/__init__.py
lib/garvit.py
Topsis1_garvit_102103471-0.0.1.dist-info/METADATA
Topsis1_garvit_102103471-0.0.1.dist-info/WHEEL
Topsis1_garvit_102103471-0.0.1.dist-info/top_level.txt
Topsis1_garvit_102103471-0.0.1.dist-info/RECORD
